lektor_tekir/__init__.py
lektor_tekir/api.py
lektor_tekir/cli.py
lektor_tekir/dash.py
lektor_tekir/utils.py
lektor_tekir/static/ball-triangle.svg
lektor_tekir/static/htmx.min.js
lektor_tekir/static/tekir-admin.css
lektor_tekir/static/tekir-admin.js
lektor_tekir/templates/tekir_attachment.html
lektor_tekir/templates/tekir_base.html
lektor_tekir/templates/tekir_content_edit.html
lektor_tekir/templates/tekir_contents.html
lektor_tekir/templates/tekir_flowblock.html
lektor_tekir/templates/tekir_macros.html
lektor_tekir/templates/tekir_overview.html
lektor_tekir/templates/icons/cloud-upload.svg
lektor_tekir/templates/icons/contents.svg
lektor_tekir/templates/icons/delete.svg
lektor_tekir/templates/icons/document-close.svg
lektor_tekir/templates/icons/document-new.svg
lektor_tekir/templates/icons/document-open-folder.svg
lektor_tekir/templates/icons/document-save.svg
lektor_tekir/templates/icons/document-swap.svg
lektor_tekir/templates/icons/edit-entry.svg
lektor_tekir/templates/icons/go-down.svg
lektor_tekir/templates/icons/go-up.svg
lektor_tekir/templates/icons/preview_sel.svg
lektor_tekir/templates/icons/run-build-clean.svg
lektor_tekir/templates/icons/run-build.svg
lektor_tekir/templates/icons/user-home.svg
lektor_tekir/templates/partials/attachment-summary.html
lektor_tekir/templates/partials/changes-dialog.html
lektor_tekir/templates/partials/content-attachments.html
lektor_tekir/templates/partials/content-subpages.html
lektor_tekir/templates/partials/content-summary.html
lektor_tekir/templates/partials/delete-dialog.html
lektor_tekir/templates/partials/error-dialog.html
lektor_tekir/templates/partials/navigables.html
lektor_tekir/templates/partials/navigate-dialog.html
lektor_tekir/templates/partials/new-subpage-dialog.html
lektor_tekir/templates/partials/publish-dialog.html
lektor_tekir/templates/partials/save-dialog.html
lektor_tekir/templates/partials/site-output.html
lektor_tekir/templates/partials/site-summary.html
lektor_tekir-0.5.dist-info/LICENSE.txt
lektor_tekir-0.5.dist-info/METADATA
lektor_tekir-0.5.dist-info/WHEEL
lektor_tekir-0.5.dist-info/entry_points.txt
lektor_tekir-0.5.dist-info/top_level.txt
lektor_tekir-0.5.dist-info/RECORD
