Metadata-Version: 2.1
Name: lektor-tekir
Version: 0.5
Summary: An alternative admin panel for Lektor.
Author-email: "H. Turgut Uyar" <uyar@tekir.org>
License: Copyright 2023 H. Turgut Uyar <uyar@tekir.org>
Project-URL: repository, https://github.com/uyar/lektor-tekir
Keywords: lektor,cms
Classifier: Development Status :: 3 - Alpha
Classifier: Environment :: Web Environment
Classifier: Framework :: Lektor
Classifier: Intended Audience :: End Users/Desktop
Classifier: License :: OSI Approved :: BSD License
Classifier: Natural Language :: English
Classifier: Natural Language :: Turkish
Classifier: Operating System :: OS Independent
Classifier: Programming Language :: Python :: 3.8
Classifier: Programming Language :: Python :: 3.9
Classifier: Programming Language :: Python :: 3.10
Classifier: Programming Language :: Python :: 3.11
Classifier: Topic :: Internet :: WWW/HTTP :: Site Management
Requires-Python: ~=3.8
License-File: LICENSE.txt
Requires-Dist: lektor
Requires-Dist: python-slugify
Requires-Dist: flask-babel
Provides-Extra: dev
Requires-Dist: lektor-tekir[style,types] ; extra == 'dev'
Requires-Dist: babel ; extra == 'dev'
Requires-Dist: build ; extra == 'dev'
Requires-Dist: twine ; extra == 'dev'
Requires-Dist: tox ; extra == 'dev'
Provides-Extra: style
Requires-Dist: ruff ; extra == 'style'
Provides-Extra: types
Requires-Dist: mypy ; extra == 'types'
Requires-Dist: types-python-slugify ; extra == 'types'
